concurrent/__init__.py
concurrent/futures/__init__.py
concurrent/futures/_base.py
concurrent/futures/process.py
concurrent/futures/thread.py
futures-3.1.1.post1.dist-info/LICENSE
futures-3.1.1.post1.dist-info/METADATA
futures-3.1.1.post1.dist-info/WHEEL
futures-3.1.1.post1.dist-info/pbr.json
futures-3.1.1.post1.dist-info/top_level.txt
futures-3.1.1.post1.dist-info/RECORD
